lms/client/__init__.py
lms/client/common_utils.py
lms/client/config.py
lms/client/deploy_module.py
lms/client/evaluate_module.py
lms/client/help_constants.py
lms/client/import_module.py
lms/client/main.py
lms/client/network_utils.py
lms/client/prune_module.py
lms/client/quantize_module.py
lms/client/validaters.py
lms/client/cluster/__init__.py
lms/client/cluster/adm.py
lms/client/daemon/__init__.py
lms/client/daemon/main.py
lms/client/daemon/nvml_util.py
lms/client/daemon/serving.py
lms/runtime/__init__.py
lms/runtime/main.py
lms/runtime/common/__init__.py
lms/runtime/common/common_utils.py
lms/runtime/common/pipeline_loader_example.py
lms/runtime/common/test.py
lms/runtime/common/traceback_utils.py
lms/runtime/deploy/__init__.py
lms/runtime/deploy/deepspeed_infer.py
lms/runtime/deploy/request.py
lms/runtime/deploy/request_body.json
lms/runtime/deploy/serving.py
lms/runtime/deploy/transformers_infer.py
lms/runtime/evaluation/__init__.py
lms/runtime/evaluation/accuracy.py
lms/runtime/evaluation/eval_module.py
lms/runtime/evaluation/manual_eval.py
lms/runtime/evaluation/benchmark/__init__.py
lms/runtime/evaluation/benchmark/accuracy.py
lms/runtime/evaluation/benchmark/dataset_loader.py
lms/runtime/evaluation/benchmark/eval.py
lms/runtime/evaluation/benchmark/eval_dataset.py
lms/runtime/evaluation/benchmark/eval_metric.py
lms/runtime/evaluation/benchmark/eval_ppl.py
lms/runtime/evaluation/benchmark/data/__init__.py
lms/runtime/evaluation/benchmark/data/AGIEval/data/few_shot_prompts.csv
lms/runtime/evaluation/benchmark/data/AGIEval/data/v1/LICENSE
lms/runtime/evaluation/benchmark/data/AGIEval/data/v1/aqua-rat.jsonl
lms/runtime/evaluation/benchmark/data/AGIEval/data/v1/gaokao-biology.jsonl
lms/runtime/evaluation/benchmark/data/AGIEval/data/v1/gaokao-chemistry.jsonl
lms/runtime/evaluation/benchmark/data/AGIEval/data/v1/gaokao-chinese.jsonl
lms/runtime/evaluation/benchmark/data/AGIEval/data/v1/gaokao-english.jsonl
dc_lms-1.0.0.dist-info/LICENSE
dc_lms-1.0.0.dist-info/METADATA
dc_lms-1.0.0.dist-info/WHEEL
dc_lms-1.0.0.dist-info/entry_points.txt
dc_lms-1.0.0.dist-info/top_level.txt
dc_lms-1.0.0.dist-info/RECORD
